carbontracker/__init__.py
carbontracker/cli.py
carbontracker/constants.py
carbontracker/exceptions.py
carbontracker/loggerutil.py
carbontracker/parser.py
carbontracker/predictor.py
carbontracker/report.py
carbontracker/tracker.py
carbontracker/utils.py
carbontracker/components/__init__.py
carbontracker/components/component.py
carbontracker/components/handler.py
carbontracker/components/apple_silicon/__init__.py
carbontracker/components/apple_silicon/powermetrics.py
carbontracker/components/cpu/__init__.py
carbontracker/components/cpu/generic.py
carbontracker/components/cpu/intel.py
carbontracker/components/cpu/sim_cpu.py
carbontracker/components/gpu/__init__.py
carbontracker/components/gpu/nvidia.py
carbontracker/components/gpu/sim_gpu.py
carbontracker/config/fetchers.json
carbontracker/data/carbon-intensities.csv
carbontracker/data/cpu_power.csv
carbontracker/emissions/__init__.py
carbontracker/emissions/conversion/__init__.py
carbontracker/emissions/conversion/co2eq.csv
carbontracker/emissions/conversion/co2eq.py
carbontracker/emissions/intensity/__init__.py
carbontracker/emissions/intensity/fetcher.py
carbontracker/emissions/intensity/intensity.py
carbontracker/emissions/intensity/location.py
carbontracker/emissions/intensity/fetchers/__init__.py
carbontracker/emissions/intensity/fetchers/carbonintensitygb.py
carbontracker/emissions/intensity/fetchers/electricitymaps.py
carbontracker/emissions/intensity/fetchers/energidataservice.py
carbontracker-2.4.4.dist-info/licenses/LICENSE
carbontracker-2.4.4.dist-info/METADATA
carbontracker-2.4.4.dist-info/WHEEL
carbontracker-2.4.4.dist-info/entry_points.txt
carbontracker-2.4.4.dist-info/top_level.txt
carbontracker-2.4.4.dist-info/RECORD
