Metadata-Version: 2.4
Name: carbontracker
Version: 2.4.4
Summary: Tracking and predicting the carbon footprint of training deep learning models.
Author: Benjamin Kanding
Author-email: "Lasse F. Wolff Anthony" <lfwa@proton.me>
License: MIT License
Project-URL: homepage, https://github.com/lfwa/carbontracker
Project-URL: repository, https://github.com/lfwa/carbontracker
Classifier: License :: OSI Approved :: MIT License
Classifier: Programming Language :: Python :: 3
Requires-Python: >=3.7
License-File: LICENSE
Requires-Dist: requests
Requires-Dist: numpy
Requires-Dist: pandas
Requires-Dist: geocoder
Requires-Dist: nvidia-ml-py
Requires-Dist: psutil
Requires-Dist: importlib-metadata
Requires-Dist: py-cpuinfo
Requires-Dist: matplotlib
Requires-Dist: seaborn
Provides-Extra: test
Requires-Dist: pyfakefs==4.5.1; python_version < "3.10" and extra == "test"
Requires-Dist: pyfakefs==5.8.0; python_version >= "3.10" and extra == "test"
Provides-Extra: docs
Requires-Dist: mkdocs; extra == "docs"
Requires-Dist: mkdocstrings[python]; extra == "docs"
Provides-Extra: pdfreport
Requires-Dist: reportlab==3.6.13; extra == "pdfreport"
Dynamic: license-file
